main.py
gendoc_cli-0.0.1.dist-info/LICENSE
gendoc_cli-0.0.1.dist-info/METADATA
gendoc_cli-0.0.1.dist-info/WHEEL
gendoc_cli-0.0.1.dist-info/entry_points.txt
gendoc_cli-0.0.1.dist-info/top_level.txt
gendoc_cli-0.0.1.dist-info/RECORD
